cloudly/__init__.py
cloudly/biglist/__init__.py
cloudly/biglist/_base.py
cloudly/biglist/_biglist.py
cloudly/biglist/_external_biglist.py
cloudly/biglist/_util.py
cloudly/biglist/parquet.py
cloudly/experimental/__init__.py
cloudly/experimental/azure/__init__.py
cloudly/experimental/azure/storage.py
cloudly/experimental/biglist/__init__.py
cloudly/experimental/gcp/alloydb.py
cloudly/experimental/gcp/logging.py
cloudly/experimental/gcp/vertexai/__init__.py
cloudly/experimental/gcp/vertexai/vector_search.py
cloudly/experimental/sql/__init__.py
cloudly/experimental/sql/postgres.py
cloudly/gcp/__init__.py
cloudly/gcp/auth.py
cloudly/gcp/batch.py
cloudly/gcp/bigquery.py
cloudly/gcp/compute.py
cloudly/gcp/logging.py
cloudly/gcp/scheduler.py
cloudly/gcp/secretmanager.py
cloudly/gcp/storage.py
cloudly/gcp/workflows.py
cloudly/gcp/sql/__init__.py
cloudly/gcp/sql/_postgres.py
cloudly/gcp/sql/postgres.py
cloudly/upathlib/__init__.py
cloudly/upathlib/_blob.py
cloudly/upathlib/_local.py
cloudly/upathlib/_upath.py
cloudly/upathlib/_util.py
cloudly/upathlib/versioned_uploadable.py
cloudly/util/__init__.py
cloudly/util/datetime.py
cloudly/util/docker.py
cloudly/util/logging.py
cloudly/util/multiplexer.py
cloudly/util/ratelimit.py
cloudly/util/seq.py
cloudly/util/serializer.py
cloudly/util/timer.py
cloudly-0.3.7.dist-info/licenses/LICENSE
cloudly-0.3.7.dist-info/WHEEL
cloudly-0.3.7.dist-info/METADATA
cloudly-0.3.7.dist-info/RECORD
