Metadata-Version: 2.4
Name: cloudly
Version: 0.3.7
Summary: Utilities for cloud computing.
Author-email: Zepu Zhang <zepu.zhang@gmail.com>
Requires-Python: >=3.10
Classifier: Intended Audience :: Developers
Classifier: Programming Language :: Python :: 3
Classifier: Topic :: Software Development :: Libraries :: Python Modules
License-File: LICENSE
Requires-Dist: filelock
Requires-Dist: orjson
Requires-Dist: pyarrow
Requires-Dist: tqdm
Requires-Dist: typing-extensions
Requires-Dist: zstandard
Requires-Dist: azure-storage-blob >=12.9.0,<13.0 ; extra == "azure"
Requires-Dist: google-cloud-bigquery ; extra == "bigquery"
Requires-Dist: google-cloud-bigquery-storage ; extra == "bigquery"
Requires-Dist: cloud-sql-python-connector[pg8000] ; extra == "cloudsql"
Requires-Dist: sphinx ; extra == "doc"
Requires-Dist: numpydoc ; extra == "doc"
Requires-Dist: pydata-sphinx-theme ; extra == "doc"
Requires-Dist: google-auth ; extra == "gcp"
Requires-Dist: google-api-core ; extra == "gcp"
Requires-Dist: google-api-python-client ; extra == "gcp"
Requires-Dist: google-cloud-batch ; extra == "gcp"
Requires-Dist: google-cloud-compute ; extra == "gcp"
Requires-Dist: google-cloud-logging ; extra == "gcp"
Requires-Dist: google-cloud-scheduler ; extra == "gcp"
Requires-Dist: google-cloud-secret-manager ; extra == "gcp"
Requires-Dist: google-cloud-storage ; extra == "gcp"
Requires-Dist: google-cloud-workflows ; extra == "gcp"
Requires-Dist: requests ; extra == "gcp"
Requires-Dist: psycopg[binary, pool] ; extra == "postgres"
Requires-Dist: fastavro ; extra == "test"
Requires-Dist: pytest-asyncio ; extra == "test"
Requires-Dist: pytest-mock ; extra == "test"
Requires-Dist: boltons ; extra == "test"
Requires-Dist: lz4 ; extra == "test"
Requires-Dist: orjson ; extra == "test"
Requires-Dist: google-cloud-aiplatform ; extra == "vertexai"
Requires-Dist: google-cloud-resource-manager ; extra == "vertexai"
Project-URL: Source, https://github.com/zpz/cloudly
Provides-Extra: azure
Provides-Extra: bigquery
Provides-Extra: cloudsql
Provides-Extra: doc
Provides-Extra: gcp
Provides-Extra: postgres
Provides-Extra: test
Provides-Extra: vertexai
